[
  {
    "名称": "伤害+",
    "层数": "0",
    "增益": "伤害",
    "消耗": "废料",
    "上限": "N/A",
    "保留": "水晶保藏室lv3"
  },
  {
    "名称": "废料增益+",
    "层数": "5",
    "增益": "废料",
    "消耗": "废料",
    "上限": "N/A",
    "保留": "水晶保藏室lv2"
  },
  {
    "名称": "废料容量+",
    "层数": "10",
    "增益": "废料容量",
    "消耗": "废料",
    "上限": "50",
    "保留": "水晶保藏室lv1"
  },
  {
    "名称": "铝存储",
    "层数": "15",
    "增益": "废料容量；铝容量",
    "消耗": "铝",
    "上限": "10",
    "保留": "成就圣遗物"
  },
  {
    "名称": "铝淬火",
    "层数": "15",
    "增益": "伤害",
    "消耗": "铝",
    "上限": "6+",
    "保留": "成就圣遗物"
  },
  {
    "名称": "制作站",
    "层数": "20",
    "增益": "解锁锻造",
    "消耗": "废料1.8M",
    "上限": "1",
    "保留": "成就圣遗物"
  },
  {
    "名称": "锻造",
    "层数": "20",
    "增益": "N/A",
    "消耗": "废料1.8M",
    "上限": "制作力量x1.2",
    "保留": "废料",
    "field7": "",
    "field8": "N/A",
    "field9": "",
    "field10": "无"
  },
  {
    "名称": "矿石槽位",
    "层数": "25",
    "增益": "矿石槽位+1",
    "消耗": "铝10",
    "上限": "1",
    "保留": "成就圣遗物"
  },
  {
    "名称": "压缩机",
    "层数": "25",
    "增益": "解锁铝压缩",
    "消耗": "铝20",
    "上限": "1",
    "保留": "成就圣遗物"
  },
  {
    "名称": "矿石槽位",
    "层数": "25",
    "增益": "矿石槽位+1",
    "消耗": "铝30",
    "上限": "1",
    "保留": "成就圣遗物"
  },
  {
    "名称": "铜存储",
    "层数": "30",
    "增益": "铝容量；铜容量",
    "消耗": "铜",
    "上限": "8",
    "保留": "成就圣遗物"
  },
  {
    "名称": "矿石槽位",
    "层数": "30",
    "增益": "矿石槽位+1",
    "消耗": "铜20",
    "上限": "1",
    "保留": "成就圣遗物"
  },
  {
    "名称": "铝罐",
    "层数": "30",
    "增益": "铝容量",
    "消耗": "废料",
    "上限": "8+",
    "保留": "成就圣遗物"
  },
  {
    "名称": "铝砧",
    "层数": "30",
    "增益": "制作力量x1.15",
    "消耗": "铝",
    "上限": "10",
    "保留": "成就圣遗物"
  },
  {
    "名称": "压缩机",
    "层数": "35",
    "增益": "解锁铜压缩",
    "消耗": "铝80",
    "上限": "1",
    "保留": "成就圣遗物"
  },
  {
    "名称": "破壳者",
    "层数": "35",
    "增益": "伤害x1.1；韧性/1.3",
    "消耗": "废料",
    "上限": "10",
    "保留": "成就圣遗物"
  },
  {
    "名称": "铜罐",
    "层数": "40",
    "增益": "铝容量；铜容量",
    "消耗": "废料",
    "上限": "5",
    "保留": "成就圣遗物"
  },
  {
    "名称": "深度居民",
    "层数": "40",
    "增益": "解锁深度居民",
    "消耗": "铜24",
    "上限": "1",
    "保留": "成就圣遗物"
  },
  {
    "名称": "铝扩张",
    "层数": "45",
    "增益": "伤害；铝容量",
    "消耗": "铝",
    "上限": "5",
    "保留": "成就圣遗物"
  },
  {
    "名称": "精炼厂",
    "层数": "45",
    "增益": "铜；铜容量",
    "消耗": "铜",
    "上限": "5+",
    "保留": "成就圣遗物"
  },
  {
    "名称": "铜扩张",
    "层数": "50",
    "增益": "伤害；铜容量",
    "消耗": "废料",
    "上限": "3",
    "保留": "成就圣遗物"
  },
  {
    "名称": "矿石槽位",
    "层数": "50",
    "增益": "矿石槽位+1",
    "消耗": "锡15",
    "上限": "1",
    "保留": "成就圣遗物"
  },
  {
    "名称": "钻机燃料",
    "层数": "50",
    "增益": "深度居民速度",
    "消耗": "废料",
    "上限": "N/A",
    "保留": "无"
  },
  {
    "名称": "花岗岩硬化",
    "层数": "55",
    "增益": "伤害x1.3",
    "消耗": "花岗岩",
    "上限": "6",
    "保留": "成就圣遗物"
  },
  {
    "名称": "冶炼厂",
    "层数": "60",
    "增益": "解锁冶炼",
    "消耗": "花岗岩50K",
    "上限": "1",
    "保留": "默认"
  },
  {
    "名称": "矿石架",
    "层数": "60",
    "增益": "锡容量",
    "消耗": "铜+铝锭5",
    "上限": "4",
    "保留": "成就圣遗物"
  },
  {
    "名称": "压缩机",
    "层数": "60",
    "增益": "解锁锡压缩",
    "消耗": "铝10K",
    "上限": "1",
    "保留": "成就圣遗物"
  },
  {
    "名称": "隔热板",
    "层数": "62",
    "增益": "冶炼温度+15",
    "消耗": "花岗岩",
    "上限": "N/A",
    "保留": "无"
  },
  {
    "名称": "锡存储",
    "层数": "65",
    "增益": "铜容量；锡容量",
    "消耗": "废料+锡",
    "上限": "4",
    "保留": "成就圣遗物"
  },
  {
    "名称": "熔炉",
    "层数": "70",
    "增益": "制作力量；矿石",
    "消耗": "废料+锡+盐",
    "上限": "25+",
    "保留": "成就圣遗物"
  },
  {
    "名称": "青铜存储",
    "层数": "75",
    "增益": "铜容量；锡容量",
    "消耗": "盐+铝锭7",
    "上限": "4",
    "保留": "成就圣遗物"
  },
  {
    "名称": "铁存储",
    "层数": "80",
    "增益": "铁容量",
    "消耗": "废料+铝锭12",
    "上限": "3",
    "保留": "成就圣遗物"
  },
  {
    "名称": "矿石槽位",
    "层数": "80",
    "增益": "矿石槽位+1",
    "消耗": "铁12",
    "上限": "1",
    "保留": "成就圣遗物"
  },
  {
    "名称": "矿石洗选",
    "层数": "82",
    "增益": "制作力量x1.1；矿石品质",
    "消耗": "废料",
    "上限": "15",
    "保留": "成就圣遗物"
  },
  {
    "名称": "铁扩张",
    "层数": "85",
    "增益": "锡容量；铁容量",
    "消耗": "铁+青铜锭4",
    "上限": "3+",
    "保留": "成就圣遗物"
  },
  {
    "名称": "铁淬火",
    "层数": "90",
    "增益": "伤害；锡容量",
    "消耗": "铁",
    "上限": "12",
    "保留": "成就圣遗物"
  },
  {
    "名称": "铁过滤器",
    "层数": "95",
    "增益": "铝容量",
    "消耗": "铁+青铜锭5",
    "上限": "8",
    "保留": "成就圣遗物"
  },
  {
    "名称": "压缩机",
    "层数": "95",
    "增益": "解锁铁压缩",
    "消耗": "铝30K",
    "上限": "1",
    "保留": "成就圣遗物"
  },
  {
    "名称": "大师锻造",
    "层数": "98",
    "增益": "伤害",
    "消耗": "煤",
    "上限": "N/A",
    "保留": "无"
  },
  {
    "名称": "星际锻造",
    "层数": "98",
    "增益": "绿水晶",
    "消耗": "煤",
    "上限": "N/A",
    "保留": "无"
  },
  {
    "名称": "磁铁",
    "层数": "100",
    "增益": "废料；矿石",
    "消耗": "废料+铁+青铜锭6",
    "上限": "10+",
    "保留": "成就圣遗物"
  },
  {
    "名称": "增强站",
    "层数": "105",
    "增益": "解锁镐增强",
    "消耗": "煤250",
    "上限": "1",
    "保留": "默认"
  },
  {
    "名称": "仓库",
    "层数": "110",
    "增益": "铝/铜/锡/铁容量x2",
    "消耗": "废料+铝锭+青铜锭",
    "上限": "12",
    "保留": "成就圣遗物"
  },
  {
    "名称": "腐蚀性烟雾",
    "层数": "112",
    "增益": "韧性/1.2",
    "消耗": "硫",
    "上限": "6",
    "保留": "无"
  },
  {
    "名称": "闻盐",
    "层数": "115",
    "增益": "制作力量x1.11",
    "消耗": "盐",
    "上限": "N/A",
    "保留": "无"
  },
  {
    "名称": "钛扩张",
    "层数": "120",
    "增益": "铁容量；钛容量",
    "消耗": "铜+锡",
    "上限": "3",
    "保留": "成就圣遗物"
  },
  {
    "名称": "矿石槽位",
    "层数": "120",
    "增益": "矿石槽位+1",
    "消耗": "钛10",
    "上限": "1",
    "保留": "成就圣遗物"
  },
  {
    "名称": "余烬锻造",
    "层数": "125",
    "增益": "余烬+1",
    "消耗": "煤",
    "上限": "N/A",
    "保留": "无"
  },
  {
    "名称": "钛存储",
    "层数": "130",
    "增益": "铜/锡/铁/钛容量",
    "消耗": "废料+钛+硫+钢锭3",
    "上限": "5",
    "保留": "成就圣遗物"
  },
  {
    "名称": "巨型锻造",
    "层数": "132",
    "增益": "余烬容量+50",
    "消耗": "煤1200x1.25^n",
    "上限": "N/A",
    "保留": "默认"
  },
  {
    "名称": "火药",
    "层数": "135",
    "增益": "伤害x1.15；废料x1.15；韧性/1.15",
    "消耗": "煤+硫+硝",
    "上限": "N/A",
    "保留": "无"
  },
  {
    "名称": "硝酸",
    "层数": "138",
    "增益": "伤害；锭强化数量/1.03",
    "消耗": "硝",
    "上限": "N/A",
    "保留": "默认"
  },
  {
    "名称": "压缩机",
    "层数": "140",
    "增益": "解锁钛压缩",
    "消耗": "铝750K",
    "上限": "1",
    "保留": "成就圣遗物"
  },
  {
    "名称": "金属探测器",
    "层数": "140",
    "增益": "废料；废料容量；钛容量",
    "消耗": "废料+钢锭",
    "上限": "12+",
    "保留": "无"
  },
  {
    "名称": "回收",
    "层数": "145",
    "增益": "废料",
    "消耗": "余烬",
    "上限": "N/A",
    "保留": "默认"
  },
  {
    "名称": "粘罐子",
    "层数": "150",
    "增益": "解锁树脂",
    "消耗": "废料4O",
    "上限": "1",
    "保留": "默认"
  },
  {
    "名称": "扫描",
    "层数": "155",
    "增益": "矿石收益x1.18",
    "消耗": "黑曜石",
    "上限": "N/A",
    "保留": "默认"
  },
  {
    "名称": "更大的面积",
    "层数": "160",
    "增益": "最大树脂+1；钛容量",
    "消耗": "废料",
    "上限": "5",
    "保留": "无"
  },
  {
    "名称": "钛锻造",
    "层数": "170",
    "增益": "制作力量x1.17；钛容量",
    "消耗": "铝锭+青铜锭+钢锭",
    "上限": "9",
    "保留": "无"
  },
  {
    "名称": "矿石槽位",
    "层数": "175",
    "增益": "矿石槽位+1",
    "消耗": "铂8",
    "上限": "1",
    "保留": "成就圣遗物"
  },
  {
    "名称": "铂扩张",
    "层数": "180",
    "增益": "钛容量；铂容量",
    "消耗": "铜+钛锭4",
    "上限": "5",
    "保留": "无"
  },
  {
    "名称": "铂钛存储",
    "层数": "190",
    "增益": "废料容量；铂容量",
    "消耗": "钛+盐+硫",
    "上限": "6",
    "保留": "无"
  },
  {
    "名称": "巨大的矿石存储",
    "层数": "200",
    "增益": "铝/铜/锡/铁/钛/铂容量x100",
    "消耗": "废料10D",
    "上限": "1",
    "保留": "无"
  },
  {
    "名称": "压缩机",
    "层数": "200",
    "增益": "解锁铂压缩",
    "消耗": "铝1B",
    "上限": "1",
    "保留": "成就圣遗物"
  },
  {
    "名称": "钛炸弹",
    "层数": "220",
    "增益": "伤害x1.2",
    "消耗": "钢锭+钛锭",
    "上限": "16",
    "保留": "无"
  },
  {
    "名称": "地下雷达",
    "层数": "240",
    "增益": "稀土x1.13",
    "消耗": "闪亮锭",
    "上限": "N/A",
    "保留": "默认"
  },
  {
    "名称": "矿石槽位",
    "层数": "260",
    "增益": "矿石槽位+1",
    "消耗": "铱6",
    "上限": "1",
    "保留": "成就圣遗物"
  },
  {
    "名称": "铱扩张",
    "层数": "260",
    "增益": "废料容量；铱容量",
    "消耗": "钛锭",
    "上限": "N/A",
    "保留": "默认"
  },
  {
    "名称": "铱存储",
    "层数": "270",
    "增益": "钛容量；铂容量；铱容量",
    "消耗": "废料+硫",
    "上限": "4",
    "保留": "无"
  },
  {
    "名称": "压缩机",
    "层数": "280",
    "增益": "解锁铱压缩",
    "消耗": "铝100T",
    "上限": "1",
    "保留": "成就圣遗物"
  },
  {
    "名称": "铱树梢",
    "层数": "280",
    "增益": "树脂容量+10；最大树脂+1",
    "消耗": "深岩+铱锭",
    "上限": "N/A",
    "保留": "默认"
  },
  {
    "名称": "大幅削减",
    "层数": "290",
    "增益": "韧性/1.25",
    "消耗": "深岩",
    "上限": "N/A",
    "保留": "无"
  },
  {
    "名称": "铱炸弹",
    "层数": "310",
    "增益": "伤害x1.23",
    "消耗": "青铜锭+铱锭",
    "上限": "7",
    "保留": "无"
  },
  {
    "名称": "矿石袋",
    "层数": "330",
    "增益": "锡容量；铁容量；钛容量；铂容量",
    "消耗": "深岩+硫",
    "上限": "12",
    "保留": "无"
  },
  {
    "名称": "锇扩张",
    "层数": "350",
    "增益": "废料容量x1.4；锇容量",
    "消耗": "闪亮锭+铱锭",
    "上限": "9",
    "保留": "无"
  },
  {
    "名称": "锇存储",
    "层数": "355",
    "增益": "锇容量",
    "消耗": "废料+深岩",
    "上限": "7",
    "保留": "无"
  },
  {
    "名称": "黑暗炸弹",
    "层数": "375",
    "增益": "伤害x1.55；废料容量x1.75",
    "消耗": "钛锭+黑铁锭",
    "上限": "10",
    "保留": "无"
  },
  {
    "名称": "巨大的废料仓库",
    "层数": "400",
    "增益": "废料容量x1000000（1M）",
    "消耗": "废料1V",
    "上限": "1",
    "保留": "无"
  },
  {
    "名称": "溶石剂",
    "层数": "425",
    "增益": "伤害x1.15；韧性/1.3",
    "消耗": "废料",
    "上限": "50",
    "保留": "无"
  },
  {
    "名称": "铅扩张",
    "层数": "450",
    "增益": "矿石容量；铅容量",
    "消耗": "黑铁锭",
    "上限": "5",
    "保留": "无"
  }
]